colorpie/__init__.py
colorpie/constants.py
colorpie/handlers.py
colorpie/mapping.py
colorpie-1.0.0.dist-info/LICENSE
colorpie-1.0.0.dist-info/METADATA
colorpie-1.0.0.dist-info/WHEEL
colorpie-1.0.0.dist-info/top_level.txt
colorpie-1.0.0.dist-info/RECORD
