Metadata-Version: 2.1
Name: colorpie
Version: 1.0.0
Summary: Terminal color style handler.
Home-page: https://github.com/ClaudiuDrug/colorpie
Author: Claudiu DRUG
Author-email: claudiu.drug@outlook.com
License: MIT License
Project-URL: Bug Tracker, https://github.com/ClaudiuDrug/colorpie/issues
Classifier: Programming Language :: Python :: 3.7
Classifier: License :: OSI Approved :: MIT License
Classifier: Operating System :: Microsoft :: Windows :: Windows 10
Classifier: Operating System :: POSIX :: Linux
Classifier: Intended Audience :: Developers
Classifier: Natural Language :: English
Classifier: Topic :: Software Development :: Libraries :: Python Modules
Classifier: Topic :: Utilities
Requires-Python: >=3.7
License-File: LICENSE
